{
  "project": "litecoin",
  "website": "litecoin.org",
  "description": "A peer-to-peer Internet currency that enables instant, near-zero cost payments to anyone in the world. Litecoin is an open source, global payment network that is fully decentralized without any central authorities. Mathematics secures the network and empowers individuals to control their own finances. Litecoin features faster transaction confirmation times and improved storage efficiency than Bitcoin.",
  "logoURL": "https://unixstickers.com/image/cache/data/stickers/litecoin/xLitecoin.sh-180x180.png.pagespeed.ic.mL2xQnrBDA.png",
  "email": "",
  "purpose": [
    "privacy",
    "decentralization"
  ],
  "type": [
    "social"
  ],
  "affiliation": "",
  "license": [
    "MIT License"
  ],
  "repoURL": "github.com/litecoin-project",
  "techDetails": {
    "languages": [
      "C++",
      "Java",
      "JavaScript",
      "Python"
    ],
    "documentation": [
      "English",
      "Czech",
      "Danish",
      "Dutch",
      "Estonian",
      "Finnish",
      "French",
      "German",
      "Italian",
      "Norwegian",
      "Polish",
      "Portuguese",
      "Slovak",
      "Spanish",
      "Swedish",
      "Turkish",
      "Vietnamese"
    ],
    "requires": "",
    "tags": ""
  }
}