{
  "project": "PubSubHubbub",
  "website": "github.com/pubsubhubbub/PubSubHubbub",
  "description": "An open protocol for distributed publish/subscribe communication on the Internet. It generalizes the concept of webhooks and allows data producers and data consumers to work in a decoupled way.\r\rPubSubHubbub provides a way to subscribe, unsubscribe and receive updates from a resource, whether it's an RSS or Atom feed or any web accessible document (JSON...).",
  "logoURL": "",
  "email": "",
  "purpose": [
    "decentralization"
  ],
  "type": [
    "social"
  ],
  "affiliation": "",
  "license": [
    ""
  ],
  "repoURL": "github.com/pubsubhubbub",
  "techDetails": {
    "languages": [
      "Go",
      "JavaScript",
      "Perl",
      "Python"
    ],
    "documentation": [
      "English"
    ],
    "requires": "",
    "tags": ""
  }
}